LICENSE
MANIFEST.in
green_ssl_module.c
pavement.py
paver-minilib.zip
setup.py
socketmodule.h
green_ssl.egg-info/PKG-INFO
green_ssl.egg-info/SOURCES.txt
green_ssl.egg-info/dependency_links.txt
green_ssl.egg-info/top_level.txt